apibrain/__init__.py
apibrain/config.py
apibrain/core.py
apibrain/decorators.py
apibrain_sdk-0.1.0.dist-info/METADATA
apibrain_sdk-0.1.0.dist-info/WHEEL
apibrain_sdk-0.1.0.dist-info/top_level.txt
apibrain_sdk-0.1.0.dist-info/RECORD
