Metadata-Version: 2.2
Name: apibrain-sdk
Version: 0.1.0
Summary: SDK para criar APIs auto-descritivas compatíveis com agentes IA
Home-page: https://github.com/system32miro/apibrain-sdk
Author: System32miro
Author-email: seu.email@exemplo.com
Classifier: Programming Language :: Python :: 3
Classifier: License :: OSI Approved :: MIT License
Classifier: Operating System :: OS Independent
Requires-Python: >=3.7
Requires-Dist: fastapi>=0.68.0
Requires-Dist: pydantic>=1.8.0
Dynamic: author
Dynamic: author-email
Dynamic: classifier
Dynamic: description
Dynamic: description-content-type
Dynamic: home-page
Dynamic: requires-dist
Dynamic: requires-python
Dynamic: summary
